{"OutputFileHashSum":"15EA4F139B5E1111C940A5C31D0708B2D78F7ED0B2DBC58C5733ADFEE6D54A7E","Converted":true,"OutputModifyDate":"2021-04-13T09:30:47.0227821Z","Metadatas":[{"CategoryName":"VuGen.Replay","Offset":258,"Length":23,"TypeId":1},{"CategoryName":"VuGen.Replay","Offset":281,"Length":59,"TypeId":2},{"CategoryName":"VuGen.Replay","Offset":426,"Length":279,"TypeId":3},{"CategoryName":"VuGen.Replay","Offset":1124,"Length":136,"TypeId":2},{"CategoryName":"VuGen.Replay","Offset":2471,"Length":51,"TypeId":2},{"CategoryName":"VuGen.Replay","Offset":3116,"Length":128,"TypeId":2},{"CategoryName":"VuGen.Replay","Offset":4155,"Length":55,"TypeId":2},{"CategoryName":"VuGen.Replay","Offset":4419,"Length":113,"TypeId":2},{"CategoryName":"VuGen.Replay","Offset":4721,"Length":55,"TypeId":2},{"CategoryName":"VuGen.Replay","Offset":5318,"Length":132,"TypeId":2},{"CategoryName":"VuGen.Replay","Offset":5890,"Length":62,"TypeId":2},{"CategoryName":"VuGen.Replay","Offset":6428,"Length":139,"TypeId":2},{"CategoryName":"VuGen.Replay","Offset":6756,"Length":63,"TypeId":2},{"CategoryName":"VuGen.Replay","Offset":7032,"Length":121,"TypeId":2},{"CategoryName":"VuGen.Replay","Offset":7707,"Length":71,"TypeId":2},{"CategoryName":"VuGen.Replay","Offset":7993,"Length":129,"TypeId":2},{"CategoryName":"VuGen.Replay","Offset":8311,"Length":66,"TypeId":2},{"CategoryName":"VuGen.Replay","Offset":8941,"Length":143,"TypeId":2},{"CategoryName":"VuGen.Replay","Offset":9273,"Length":60,"TypeId":2},{"CategoryName":"VuGen.Replay","Offset":9825,"Length":137,"TypeId":2},{"CategoryName":"VuGen.Replay","Offset":10151,"Length":44,"TypeId":2},{"CategoryName":"VuGen.Replay","Offset":11919,"Length":103,"TypeId":2},{"CategoryName":"VuGen.Replay","Offset":12022,"Length":52,"TypeId":2},{"CategoryName":"VuGen.Replay","Offset":12285,"Length":110,"TypeId":2},{"CategoryName":"VuGen.Replay","Offset":12584,"Length":21,"TypeId":1},{"CategoryName":"VuGen.Replay","Offset":12605,"Length":23,"TypeId":1},{"CategoryName":"VuGen.Replay","Offset":12628,"Length":59,"TypeId":2},{"CategoryName":"VuGen.Replay","Offset":13192,"Length":136,"TypeId":2},{"CategoryName":"VuGen.Replay","Offset":14539,"Length":51,"TypeId":2},{"CategoryName":"VuGen.Replay","Offset":15184,"Length":128,"TypeId":2},{"CategoryName":"VuGen.Replay","Offset":16223,"Length":55,"TypeId":2},{"CategoryName":"VuGen.Replay","Offset":16487,"Length":113,"TypeId":2},{"CategoryName":"VuGen.Replay","Offset":16789,"Length":55,"TypeId":2},{"CategoryName":"VuGen.Replay","Offset":17386,"Length":132,"TypeId":2},{"CategoryName":"VuGen.Replay","Offset":17958,"Length":62,"TypeId":2},{"CategoryName":"VuGen.Replay","Offset":18496,"Length":139,"TypeId":2},{"CategoryName":"VuGen.Replay","Offset":18824,"Length":63,"TypeId":2},{"CategoryName":"VuGen.Replay","Offset":19100,"Length":121,"TypeId":2},{"CategoryName":"VuGen.Replay","Offset":19775,"Length":71,"TypeId":2},{"CategoryName":"VuGen.Replay","Offset":20061,"Length":129,"TypeId":2},{"CategoryName":"VuGen.Replay","Offset":20379,"Length":66,"TypeId":2},{"CategoryName":"VuGen.Replay","Offset":21009,"Length":143,"TypeId":2},{"CategoryName":"VuGen.Replay","Offset":21341,"Length":60,"TypeId":2},{"CategoryName":"VuGen.Replay","Offset":21893,"Length":137,"TypeId":2},{"CategoryName":"VuGen.Replay","Offset":22219,"Length":44,"TypeId":2},{"CategoryName":"VuGen.Replay","Offset":23987,"Length":103,"TypeId":2},{"CategoryName":"VuGen.Replay","Offset":24090,"Length":52,"TypeId":2},{"CategoryName":"VuGen.Replay","Offset":24353,"Length":110,"TypeId":2},{"CategoryName":"VuGen.Replay","Offset":24652,"Length":21,"TypeId":1},{"CategoryName":"VuGen.Replay","Offset":24673,"Length":23,"TypeId":1},{"CategoryName":"VuGen.Replay","Offset":24696,"Length":59,"TypeId":2},{"CategoryName":"VuGen.Replay","Offset":25260,"Length":136,"TypeId":2},{"CategoryName":"VuGen.Replay","Offset":26607,"Length":51,"TypeId":2},{"CategoryName":"VuGen.Replay","Offset":27252,"Length":128,"TypeId":2},{"CategoryName":"VuGen.Replay","Offset":28291,"Length":55,"TypeId":2},{"CategoryName":"VuGen.Replay","Offset":28555,"Length":113,"TypeId":2},{"CategoryName":"VuGen.Replay","Offset":28857,"Length":55,"TypeId":2},{"CategoryName":"VuGen.Replay","Offset":29454,"Length":132,"TypeId":2},{"CategoryName":"VuGen.Replay","Offset":30026,"Length":62,"TypeId":2},{"CategoryName":"VuGen.Replay","Offset":30564,"Length":139,"TypeId":2},{"CategoryName":"VuGen.Replay","Offset":30892,"Length":63,"TypeId":2},{"CategoryName":"VuGen.Replay","Offset":31168,"Length":121,"TypeId":2},{"CategoryName":"VuGen.Replay","Offset":31843,"Length":71,"TypeId":2},{"CategoryName":"VuGen.Replay","Offset":32129,"Length":129,"TypeId":2},{"CategoryName":"VuGen.Replay","Offset":32447,"Length":66,"TypeId":2},{"CategoryName":"VuGen.Replay","Offset":33077,"Length":143,"TypeId":2},{"CategoryName":"VuGen.Replay","Offset":33409,"Length":60,"TypeId":2},{"CategoryName":"VuGen.Replay","Offset":33961,"Length":137,"TypeId":2},{"CategoryName":"VuGen.Replay","Offset":34287,"Length":44,"TypeId":2},{"CategoryName":"VuGen.Replay","Offset":36055,"Length":103,"TypeId":2},{"CategoryName":"VuGen.Replay","Offset":36158,"Length":52,"TypeId":2},{"CategoryName":"VuGen.Replay","Offset":36421,"Length":110,"TypeId":2},{"CategoryName":"VuGen.Replay","Offset":36720,"Length":21,"TypeId":1}],"MetadataTypes":[{"CategoryName":"VuGen.Replay","MetadataTypeName":"HP.LR.Vugen.Iteration","Id":1},{"CategoryName":"VuGen.Replay","MetadataTypeName":"HP.LR.Vugen.NotifyTransaction","Id":2},{"CategoryName":"VuGen.Replay","MetadataTypeName":"Utt.Debugger.Warning","Id":3},{"CategoryName":"VuGen.Replay","MetadataTypeName":"Utt.Debugger.Error","Id":4},{"CategoryName":"VuGen.Replay","MetadataTypeName":"HP.LR.Vugen.NotifyAny","Id":5}]}